Metadata-Version: 2.1
Name: fasthaversine
Version: 0.1.2
Summary: A fast vectorized version of haversine distance calculation.
Home-page: https://github.com/qyliu-hkust/fasthaversine
Author: Qiyu Liu
Author-email: keiyuk.liu@gmail.com
Maintainer: Qiyu Liu
Maintainer-email: keiyuk.liu@gmail.com
License: ['MIT']
Download-URL: https://github.com/qyliu-hkust/fasthaversine/archive/0.1.2.tar.gz
Platform: UNKNOWN
Classifier: Development Status :: 4 - Beta
Classifier: Intended Audience :: Developers
Classifier: License :: OSI Approved :: MIT License
Classifier: Programming Language :: Python :: 3
Classifier: Programming Language :: Python :: 3.1
Classifier: Programming Language :: Python :: 3.2
Classifier: Programming Language :: Python :: 3.3
Classifier: Programming Language :: Python :: 3.4
Classifier: Programming Language :: Python :: 3.5
Classifier: Programming Language :: Python :: 3.6
Classifier: Programming Language :: Python :: 3.7
Classifier: Topic :: Scientific/Engineering :: Mathematics
